pysh/__init__.py
pysh/pype.py
pysh/serializer.py
pysh/utils.py
pyshpype-0.1.2.dist-info/METADATA
pyshpype-0.1.2.dist-info/WHEEL
pyshpype-0.1.2.dist-info/RECORD
