Metadata-Version: 2.1
Name: pyshpype
Version: 0.1.2
Summary: Run shell in python
Home-page: https://github.com/blipk/pysh
License: MIT
Keywords: pysh,shell,bash
Author: Blipk A.D.
Requires-Python: >=3.10
Classifier: License :: OSI Approved :: MIT License
Classifier: Programming Language :: Python :: 3
Classifier: Programming Language :: Python :: 3.10
Classifier: Programming Language :: Python :: 3.11
Classifier: Topic :: Software Development :: Libraries :: Python Modules
Project-URL: Documentation, https://github.com/blipk/pysh
Project-URL: Repository, https://github.com/blipk/pysh
